{"InputModulePart":[{"name":"","keyActions":[{"mAction":"Defense","KeyCode":113},{"mAction":"Attack","KeyCode":101},{"mAction":"Jump","KeyCode":32},{"mAction":"WeaponChange","KeyCode":9},{"mAction":"Dodge","KeyCode":304},{"mAction":"Skill","KeyCode":102}],"mouseActions":[{"mAction":"Attack","mouseButton":0},{"mAction":"SAttack","mouseButton":1},{"mAction":"Lock","mouseButton":2}],"ComboInputActions":[{"keyGroup":[119,119,-1],"mAction":"Skill_Rush"},{"keyGroup":[115,119,-1],"mAction":"Skill_Rear"},{"keyGroup":[115,100,115,100,106],"mAction":"Skill"},{"keyGroup":[115,100,115,100,107],"mAction":"Skill_Rush"},{"keyGroup":[97,115,97,115,106],"mAction":"Skill_Rear"}],"KeyCombinAtions":[],"moveInput":0,"viewInput":1}],"InputSystemID":0}